<TextureAtlas imagePath="sprites.png">
	<SubTexture name="Rune_Aquarius.png" x="0" y="432" width="24" height="23"/>
	<SubTexture name="Rune_Aries.png" x="26" y="407" width="24" height="23"/>
	<SubTexture name="Rune_Cancer.png" x="0" y="457" width="24" height="23"/>
	<SubTexture name="Rune_Fire.png" x="52" y="426" width="24" height="23"/>
	<SubTexture name="Rune_Gemini.png" x="52" y="451" width="24" height="23"/>
	<SubTexture name="Rune_Ice.png" x="52" y="476" width="24" height="23"/>
	<SubTexture name="Rune_Leo.png" x="52" y="351" width="24" height="23"/>
	<SubTexture name="Rune_Libra.png" x="52" y="376" width="24" height="23"/>
	<SubTexture name="Rune_Pisces.png" x="52" y="326" width="24" height="23"/>
	<SubTexture name="Rune_Sagittarius.png" x="52" y="401" width="24" height="23"/>
	<SubTexture name="Rune_Scorpio.png" x="26" y="482" width="24" height="23"/>
	<SubTexture name="Rune_Taurus.png" x="26" y="457" width="24" height="23"/>
	<SubTexture name="Rune_Virgo.png" x="26" y="432" width="24" height="23"/>
	<SubTexture name="Rune_Water.png" x="26" y="356" width="24" height="23"/>
	<SubTexture name="Rune_blank.png" x="78" y="302" width="24" height="23"/>
	<SubTexture name="Rune_capricorn.png" x="0" y="482" width="24" height="23"/>
	<SubTexture name="blue.png" x="67" y="316" width="6" height="4"/>
	<SubTexture name="bush.png" x="0" y="330" width="24" height="24"/>
	<SubTexture name="bushSnowy.png" x="33" y="302" width="24" height="22"/>
	<SubTexture name="cannon_tower.png" x="103" y="353" width="16" height="31"/>
	<SubTexture name="coin.png" x="146" y="302" width="12" height="12"/>
	<SubTexture name="cross.png" x="102" y="482" width="18" height="18"/>
	<SubTexture name="glaq.png" x="102" y="466" width="18" height="14"/>
	<SubTexture name="glaqnax_blood_knight.png" x="102" y="442" width="21" height="22"/>
	<SubTexture name="green.png" x="59" y="316" width="6" height="4"/>
	<SubTexture name="lake.png" x="78" y="486" width="22" height="21"/>
	<SubTexture name="mage.png" x="0" y="302" width="31" height="26"/>
	<SubTexture name="menu-background.png" x="0" y="0" width="480" height="300"/>
	<SubTexture name="red.png" x="52" y="501" width="6" height="4"/>
	<SubTexture name="rock_tower.png" x="78" y="404" width="22" height="30"/>
	<SubTexture name="s1_tile_01.png" x="123" y="316" width="12" height="12"/>
	<SubTexture name="s1_tile_02.png" x="123" y="330" width="12" height="12"/>
	<SubTexture name="s1_tile_03.png" x="117" y="386" width="12" height="12"/>
	<SubTexture name="s1_tile_04.png" x="104" y="302" width="12" height="12"/>
	<SubTexture name="s1_tile_05.png" x="103" y="386" width="12" height="12"/>
	<SubTexture name="s1_tile_06.png" x="59" y="302" width="12" height="12"/>
	<SubTexture name="s1_tile_07.png" x="145" y="372" width="12" height="12"/>
	<SubTexture name="s1_tile_08.png" x="118" y="302" width="12" height="12"/>
	<SubTexture name="s1_tile_09.png" x="132" y="302" width="12" height="12"/>
	<SubTexture name="s1_tile_10.png" x="139" y="440" width="12" height="12"/>
	<SubTexture name="s1_tile_11.png" x="139" y="426" width="12" height="12"/>
	<SubTexture name="s1_tile_12.png" x="121" y="353" width="12" height="12"/>
	<SubTexture name="s1_tile_13.png" x="121" y="367" width="12" height="12"/>
	<SubTexture name="s1_tile_14.png" x="122" y="466" width="12" height="12"/>
	<SubTexture name="s1_tile_15.png" x="122" y="480" width="12" height="12"/>
	<SubTexture name="s1_tile_16.png" x="122" y="494" width="12" height="12"/>
	<SubTexture name="s2_tile_01.png" x="136" y="498" width="12" height="12"/>
	<SubTexture name="s2_tile_02.png" x="139" y="412" width="12" height="12"/>
	<SubTexture name="s2_tile_03.png" x="137" y="330" width="12" height="12"/>
	<SubTexture name="s2_tile_04.png" x="125" y="400" width="12" height="12"/>
	<SubTexture name="s2_tile_05.png" x="125" y="414" width="12" height="12"/>
	<SubTexture name="s2_tile_06.png" x="125" y="428" width="12" height="12"/>
	<SubTexture name="s2_tile_07.png" x="125" y="442" width="12" height="12"/>
	<SubTexture name="s2_tile_08.png" x="131" y="381" width="12" height="12"/>
	<SubTexture name="s2_tile_09.png" x="135" y="344" width="12" height="12"/>
	<SubTexture name="s2_tile_10.png" x="135" y="358" width="12" height="12"/>
	<SubTexture name="s2_tile_11.png" x="136" y="456" width="12" height="12"/>
	<SubTexture name="s2_tile_12.png" x="136" y="470" width="12" height="12"/>
	<SubTexture name="s2_tile_13.png" x="136" y="484" width="12" height="12"/>
	<SubTexture name="s2_tile_14.png" x="137" y="316" width="12" height="12"/>
	<SubTexture name="spawn_of_zax.png" x="139" y="395" width="12" height="15"/>
	<SubTexture name="stone-0.png" x="78" y="327" width="23" height="23"/>
	<SubTexture name="stone-1.png" x="26" y="381" width="24" height="24"/>
	<SubTexture name="stone-2.png" x="78" y="436" width="22" height="23"/>
	<SubTexture name="stone-3.png" x="26" y="330" width="24" height="24"/>
	<SubTexture name="stone-4.png" x="78" y="461" width="22" height="23"/>
	<SubTexture name="stone-5.png" x="78" y="378" width="23" height="24"/>
	<SubTexture name="stone-6.png" x="78" y="352" width="23" height="24"/>
	<SubTexture name="stone-7.png" x="0" y="406" width="24" height="24"/>
	<SubTexture name="treeBush.png" x="0" y="356" width="24" height="48"/>
	<SubTexture name="treeSnowy.png" x="102" y="404" width="21" height="36"/>
	<SubTexture name="watch_tower.png" x="103" y="327" width="18" height="24"/>
	<SubTexture name="yellow.png" x="60" y="501" width="6" height="4"/>
</TextureAtlas>